Metadata-Version: 2.1
Name: jobpy
Version: 0.0.7
Summary: A package built to facilitate job search and match your skills the best job.
Home-page: https://github.com/rodrez/jobpy
Author: Fabian Rodriguez
Author-email: fabian.rodrez@gmail.com
License: MIT
Keywords: jobs,jobpy,job tool
Platform: UNKNOWN
Classifier: Development Status :: 3 - Alpha
Classifier: Topic :: Software Development :: Build Tools
Classifier: Programming Language :: Python :: 3
Classifier: License :: OSI Approved :: MIT License
Classifier: Operating System :: OS Independent
